CHANGELOG.txt
LICENCE.txt
MANIFEST.in
README.txt
setup.py
tuyentestpylib/__init__.py
tuyentestpylib/npf.py
tuyentestpylib.egg-info/PKG-INFO
tuyentestpylib.egg-info/SOURCES.txt
tuyentestpylib.egg-info/dependency_links.txt
tuyentestpylib.egg-info/requires.txt
tuyentestpylib.egg-info/top_level.txt